{
  "required": true,
  "minVersion": "0.8",
  "package": "dev.tonimatas.packetfixer.mixins",
  "compatibilityLevel": "JAVA_18",
  "mixins": [
    "ClientboundCustomQueryPacketMixin",
    "ClientboundLevelChunkPacketDataMixin",
    "CompressionDecoderMixin",
    "CompressionEncoderMixin",
    "ConnectionMixin",
    "FriendlyByteBufMixin",
    "MinecraftServerMixin",
    "NbtAccounterMixin",
    "ServerboundCustomQueryPacketMixin",
    "ServerCommonPacketListenerImplMixin",
    "ServerConnectionListenerMixin",
    "ServerLoginPacketListenerImplMixin",
    "Varint21FrameDecoderMixin",
    "Varint21LengthFieldPrependerMixin",
    "VarIntMixin",
    "VarLongMixin"
  ],
  "injectors": {
    "defaultRequire": 0
  }
}
