{
  "client": [
  ],
  "compatibilityLevel": "JAVA_8",
  "injectors": {
    "defaultRequire": 1
  },
  "minVersion": "0.8",
  "mixins": [
    "CCustomPayloadLoginPacketMixin",
    "CCustomPayloadPacketMixin",
    "NettyCompressionDecoderMixin",
    "NettyCompressionEncoderMixin",
    "SCustomPayloadLoginPacketMixin",
    "SCustomPayloadPacketMixin",
    "ServerLoginNetHandlerMixin"
  ],
  "package": "net.tonimatasdev.packetsizedoublerforge.mixin",
  "refmap": "packetsizedoublerforge.refmap.json",
  "required": true
}
